serenity/__init__.py
serenity/serenity.py
serenity-0.1.0.dist-info/METADATA
serenity-0.1.0.dist-info/RECORD
serenity-0.1.0.dist-info/WHEEL
serenity-0.1.0.dist-info/top_level.txt
