Metadata-Version: 2.1
Name: serenity
Version: 0.1.0
Summary: Renderfarm framework
Home-page: https://github.com/aldmbmtl/serenity
Author: Alex Hatfield
Author-email: alex@hatfieldfx.com
License: MIT license
Keywords: serenity
Platform: UNKNOWN
Classifier: Development Status :: 2 - Pre-Alpha
Classifier: Intended Audience :: Developers
Classifier: License :: OSI Approved :: MIT License
Classifier: Natural Language :: English
Classifier: Programming Language :: Python :: 2
Classifier: Programming Language :: Python :: 2.7
Classifier: Programming Language :: Python :: 3
Classifier: Programming Language :: Python :: 3.4
Classifier: Programming Language :: Python :: 3.5
Classifier: Programming Language :: Python :: 3.6
Classifier: Programming Language :: Python :: 3.7
Requires-Dist: app-net
